[
    { 
        "name": "Rage", 
        "dependancy": null,
        "conflifts": [null], 
        "tier": 1,
        "stackable":false
    },
    { 
        "name": "Unarmored Defense", 
        "dependancy": null,
        "conflifts": [null], 
        "tier": 1,
        "stackable":false 
    },
    { 
        "name": "Reckless Attack", 
        "dependancy": null,
        "conflifts": [null], 
        "tier": 1,
        "stackable":false 
    },
    { 
        "name": "Danger Sense", 
        "dependancy": null,
        "conflifts": [null], 
        "tier": 1,
        "stackable":false 
    },
    { 
        "name": "Extra Attack", 
        "dependancy": null,
        "conflifts": [null], 
        "tier": 1,
        "stackable":true 
    },
    { 
        "name": "Fast Movement", 
        "dependancy": null,
        "conflifts": [null], 
        "tier": 1,
        "stackable":false 
    },
    { 
        "name": "Feral Instinct", 
        "dependancy": null,
        "conflifts": [null], 
        "tier": 2,
        "stackable":false 
    },
    { 
        "name": "Brutal Critical", 
        "dependancy": null,
        "conflifts": [null], 
        "tier": 2,
        "stackable":false 
    },
    { 
        "name": "Relentless Rage", 
        "dependancy": "Rage",
        "conflifts": [null], 
        "tier": 2,
        "stackable":false 
    },
    { 
        "name": "Persistent Rage", 
        "dependancy": "Rage",
        "conflifts": [null], 
        "tier": 3,
        "stackable":false 
    },
    { 
        "name": "Indomitable Might", 
        "dependancy": null,
        "conflifts": [null], 
        "tier": 3,
        "stackable":false 
    },
    { 
        "name": "Primal Champion", 
        "dependancy": null,
        "conflifts": [null], 
        "tier": 3,
        "stackable":false 
    },
    { 
        "name": "Bardic Inspiration", 
        "dependancy": null,
        "conflifts": [null], 
        "tier": 1,
        "stackable":false 
    },
    { 
        "name": "Wild Shape", 
        "dependancy": null,
        "conflifts": [null], 
        "tier": 1,
        "stackable":false 
    },
    { 
        "name": "Archdruid", 
        "dependancy": "Wild Shape",
        "conflifts": [null], 
        "tier": 3,
        "stackable":false 
    },
    { 
        "name": "Fighting Style (Fighter)", 
        "dependancy": null,
        "conflifts": [null], 
        "tier": 1,
        "stackable":false 
    },
    { 
        "name": "Second Wind", 
        "dependancy": null,
        "conflifts": [null], 
        "tier": 1,
        "stackable":false 
    },
    { 
        "name": "Action Surge", 
        "dependancy": null,
        "conflifts": [null], 
        "tier": 2,
        "stackable":false 
    },
    { 
        "name": "Indomitable", 
        "dependancy": null,
        "conflifts": [null], 
        "tier": 2,
        "stackable":false 
    },
    { 
        "name": "Martial Arts", 
        "dependancy": null,
        "conflifts": [null], 
        "tier": 1,
        "stackable":false 
    },
    { 
        "name": "Ki", 
        "dependancy": null,
        "conflifts": [null], 
        "tier": 1,
        "stackable":false 
    },
    { 
        "name": "Unarmored Movement", 
        "dependancy": null,
        "conflifts": [null], 
        "tier": 2,
        "stackable":false 
    },
    { 
        "name": "Deflect Missiles", 
        "dependancy": null,
        "conflifts": [null], 
        "tier": 2,
        "stackable":false 
    },
    { 
        "name": "Stunning Strike", 
        "dependancy": "Ki",
        "conflifts": [null], 
        "tier": 2,
        "stackable":false 
    },
    {
        "name": "Ki-Empowered Strikes",
        "dependancy": "Ki",
        "conflifts": [null],
        "tier": 2,
        "stackable":false

    },
    { 
        "name": "Evasion", 
        "dependancy": null,
        "conflifts": [null], 
        "tier": 2,
        "stackable":false 
    },
    { 
        "name": "Diamond Soul", 
        "dependancy": "Ki",
        "conflifts": [null], 
        "tier": 3,
        "stackable":false 
    },
    {
        "name": "Empty Body",
        "dependancy": "Ki",
        "conflifts": [null],
        "tier": 3,
        "stackable":false
    },
    { 
        "name": "Fighting Style (Ranger)", 
        "dependancy": null,
        "conflifts": [null], 
        "tier": 1,
        "stackable":false 
    },
    { 
        "name": "Foe Slayer", 
        "dependancy": null,
        "conflifts": [null], 
        "tier": 3,
        "stackable":false 
    },
    { 
        "name": "Sneak Attack", 
        "dependancy": null,
        "conflifts": [null], 
        "tier": 1,
        "stackable":false 
    },
    { 
        "name": "Cunning Action", 
        "dependancy": null,
        "conflifts": [null], 
        "tier": 1,
        "stackable":false 
    },
    { 
        "name": "Uncanny Dodge", 
        "dependancy": null,
        "conflifts": [null], 
        "tier": 2,
        "stackable":false 
    },
    { 
        "name": "Reliable Talent", 
        "dependancy": null,
        "conflifts": [null], 
        "tier": 2,
        "stackable":false 
    },
    { 
        "name": "Blindsense", 
        "dependancy": null,
        "conflifts": [null], 
        "tier": 3,
        "stackable":false 
    },
    { 
        "name": "Elusive", 
        "dependancy": null,
        "conflifts": [null], 
        "tier": 3,
        "stackable":false 
    },
    { 
        "name": "Stroke of Luck", 
        "dependancy": null,
        "conflifts": [null], 
        "tier": 3,
        "stackable":false 
    },
    { 
        "name": "Ability Score Improvement", 
        "dependancy": null,
        "conflifts": [null], 
        "tier": null,
        "stackable":true 
    },
    {
        "name":"Shield Master",
        "dependancy":null,
        "conflifts":[null],
        "tier":null,
        "stackable":false,
        "link":"http://dnd5e.wikidot.com/feat:shield-master"
    },
    {
        "name":"Sentinel",
        "dependancy":null,
        "conflifts":[null],
        "tier":null,
        "stackable":false,
        "link":"http://dnd5e.wikidot.com/feat:sentinel"
    },
    {
        "name":"Savage Attacker",
        "dependancy":null,
        "conflifts":[null],
        "tier":null,
        "stackable":false,
        "link":"http://dnd5e.wikidot.com/feat:savage-attacker"
    },
    {
        "name":"Polearm Master",
        "dependancy":null,
        "conflifts":[null],
        "tier":null,
        "stackable":false,
        "link":"http://dnd5e.wikidot.com/feat:polearm-master"
    },
    {
        "name":"Heavy Armor Master",
        "dependancy":null,
        "conflifts":[null],
        "tier":null,
        "stackable":false,
        "link":"http://dnd5e.wikidot.com/feat:heavy-armor-master"
    },
    {
        "name":"Great Weapon Master",
        "dependancy":null,
        "conflifts":[null],
        "tier":null,
        "stackable":false,
        "link":"http://dnd5e.wikidot.com/feat:great-weapon-master"
    },
    {
        "name":"Dual Wielder",
        "dependancy":null,
        "conflifts":[null],
        "tier":null,
        "stackable":false,
        "link":"http://dnd5e.wikidot.com/feat:dual-wielder"
    },
    {
        "name":"Defensive Duelist",
        "dependancy":null,
        "conflifts":[null],
        "tier":null,
        "stackable":false,
        "link":"http://dnd5e.wikidot.com/feat:defensive-duelist"
    }
]